{
  "material": [],
  "strategy": [
    {
      "author": "HoYo青枫",
      "article": "65751982",
      "url": "https://gitee.com/qsyhh_res/image/raw/master/sr/白厄/HoYo青枫_65751982.jpg"
    },
    {
      "author": "让我摸个鱼吧Moyu",
      "article": "65744995",
      "url": "https://gitee.com/qsyhh_res/image/raw/master/sr/白厄/让我摸个鱼吧Moyu_65744995.jpg"
    },
    {
      "author": "小橙子阿",
      "article": "65744938",
      "url": "https://gitee.com/qsyhh_res/image/raw/master/sr/白厄/小橙子阿_65744938.jpg"
    },
    {
      "author": "祈鸢ya",
      "article": "65744980",
      "url": "https://upload-bbs.miyoushe.com/upload/2025/06/25/137101761/004ed06a670b1e98191014f98b54b184_895279523947925481.png"
    }
  ]
}